[
    {
        "type": "message",
        "user": "U3U0TU7K9",
        "text": "Had another look at the Weebly. Those cool crocs? <https:\/\/en.m.wikipedia.org\/wiki\/Cool_Croc_Twins>",
        "attachments": [
            {
                "title": "Cool Croc Twins",
                "title_link": "https:\/\/en.m.wikipedia.org\/wiki\/Cool_Croc_Twins",
                "author_name": "Wikipedia",
                "author_link": "http:\/\/en.wikipedia.org\/",
                "text": "Cool Croc Twins is a platform game developed by Arcade Masters and published by Empire Software for the Amiga, Atari ST, Commodore 64, and MS-DOS in 1991. The player controls one of two crocodile twins named \"Funk\" and \"Punk\" respectively in an attempt to rescue a crocodile girl.",
                "fallback": "wikipedia: Cool Croc Twins",
                "service_icon": "https:\/\/a.slack-edge.com\/bfaba\/img\/unfurl_icons\/wikipedia.png",
                "id": 1
            }
        ],
        "ts": "1487235599.000113",
        "reactions": [
            {
                "name": "crocodile",
                "users": [
                    "U3P3ZG1Q9",
                    "U3QAZR6D6",
                    "U3PTX9WER"
                ],
                "count": 3
            }
        ]
    },
    {
        "type": "message",
        "user": "U3P3ZG1Q9",
        "text": "Omg omg THAT'S TOTALLY THEM!! :D",
        "ts": "1487244614.000115"
    },
    {
        "type": "message",
        "user": "U3P3ZG1Q9",
        "text": "<@U3U0TU7K9>, you ROCK!",
        "ts": "1487244637.000116"
    },
    {
        "type": "message",
        "subtype": "file_share",
        "text": "<@U3P3ZG1Q9> uploaded a file: <https:\/\/nerdpartytrivia.slack.com\/files\/U3P3ZG1Q9\/F46D2D2BX\/3087_dbs1.png|Cool Crocs>",
        "file": {
            "id": "F46D2D2BX",
            "created": 1487244731,
            "timestamp": 1487244731,
            "name": "3087_dbs1.png",
            "title": "Cool Crocs",
            "mimetype": "image\/png",
            "filetype": "png",
            "pretty_type": "PNG",
            "user": "U3P3ZG1Q9",
            "editable": false,
            "size": 35851,
            "mode": "hosted",
            "is_external": false,
            "external_type": "",
            "is_public": true,
            "public_url_shared": false,
            "display_as_bot": false,
            "username": "",
            "url_private": "https:\/\/files.slack.com\/files-pri\/T3P35HN56-F46D2D2BX\/3087_dbs1.png?t=xoxe-125107600176-274565733731-275515188566-de7bec41ca",
            "url_private_download": "https:\/\/files.slack.com\/files-pri\/T3P35HN56-F46D2D2BX\/download\/3087_dbs1.png?t=xoxe-125107600176-274565733731-275515188566-de7bec41ca",
            "thumb_64": "https:\/\/files.slack.com\/files-tmb\/T3P35HN56-F46D2D2BX-ac04d43bac\/3087_dbs1_64.png?t=xoxe-125107600176-274565733731-275515188566-de7bec41ca",
            "thumb_80": "https:\/\/files.slack.com\/files-tmb\/T3P35HN56-F46D2D2BX-ac04d43bac\/3087_dbs1_80.png?t=xoxe-125107600176-274565733731-275515188566-de7bec41ca",
            "thumb_360": "https:\/\/files.slack.com\/files-tmb\/T3P35HN56-F46D2D2BX-ac04d43bac\/3087_dbs1_360.png?t=xoxe-125107600176-274565733731-275515188566-de7bec41ca",
            "thumb_360_w": 360,
            "thumb_360_h": 144,
            "thumb_480": "https:\/\/files.slack.com\/files-tmb\/T3P35HN56-F46D2D2BX-ac04d43bac\/3087_dbs1_480.png?t=xoxe-125107600176-274565733731-275515188566-de7bec41ca",
            "thumb_480_w": 480,
            "thumb_480_h": 192,
            "thumb_160": "https:\/\/files.slack.com\/files-tmb\/T3P35HN56-F46D2D2BX-ac04d43bac\/3087_dbs1_160.png?t=xoxe-125107600176-274565733731-275515188566-de7bec41ca",
            "image_exif_rotation": 1,
            "original_w": 640,
            "original_h": 256,
            "permalink": "https:\/\/nerdpartytrivia.slack.com\/files\/U3P3ZG1Q9\/F46D2D2BX\/3087_dbs1.png",
            "permalink_public": "https:\/\/slack-files.com\/T3P35HN56-F46D2D2BX-3315ffe6e6",
            "channels": [],
            "groups": [],
            "ims": [],
            "comments_count": 0
        },
        "user": "U3P3ZG1Q9",
        "upload": true,
        "display_as_bot": false,
        "username": "autumn",
        "bot_id": null,
        "ts": "1487244731.000117"
    },
    {
        "type": "message",
        "user": "U3QAZR6D6",
        "text": "Awesome! ",
        "ts": "1487251473.000120"
    },
    {
        "type": "message",
        "user": "U3SJ6J3CZ",
        "text": "Holy wow!!! Awesome job!!!! :smile:",
        "ts": "1487254819.000121"
    },
    {
        "type": "message",
        "user": "U3QGW9KML",
        "text": "i have a hulu sub",
        "ts": "1487254869.000122"
    },
    {
        "type": "message",
        "user": "U3TAVES85",
        "text": "I knew he looked like 90s video game mascot",
        "ts": "1487257502.000128"
    },
    {
        "type": "message",
        "user": "U3SJ6J3CZ",
        "text": "Have some of us seen \"Sharknado\" or any of the sequels? I haven't seen any of them. ",
        "ts": "1487258240.000129"
    },
    {
        "type": "message",
        "user": "U3P3ZG1Q9",
        "text": "My mom has seen them all. :wink:",
        "ts": "1487258820.000130"
    },
    {
        "type": "message",
        "user": "U3SJ6J3CZ",
        "text": "Have her on speed-dial! :joy:",
        "ts": "1487261812.000131"
    },
    {
        "type": "message",
        "user": "U3P3ZG1Q9",
        "text": "No way I'd get the answer before we needed it. She likes to talk a lot... I'd hear all about what the cats are doing, what happened in the 2 previous Sharknados, how that relates to something in a Twilight Zone episode, which actors were in that Twilight Zone episode... what was the question again?",
        "ts": "1487262195.000132",
        "reactions": [
            {
                "name": "joy",
                "users": [
                    "U3SJ6J3CZ",
                    "U3PSHA2RY",
                    "U3V9ED7FG"
                ],
                "count": 3
            }
        ]
    },
    {
        "type": "message",
        "user": "U3THCEWQL",
        "text": "My sister in law loves those movies. It makes Chris and I sad because she says she never has time to watch actual good shows. :smiley:",
        "ts": "1487262237.000133",
        "reactions": [
            {
                "name": "fish",
                "users": [
                    "U3P3ZG1Q9"
                ],
                "count": 1
            },
            {
                "name": "tornado",
                "users": [
                    "U3P3ZG1Q9"
                ],
                "count": 1
            }
        ]
    },
    {
        "type": "message",
        "subtype": "file_share",
        "text": "<@U3SJ6J3CZ> uploaded a file: <https:\/\/nerdpartytrivia.slack.com\/files\/U3SJ6J3CZ\/F45S19ZG9\/image_uploaded_from_ios.jpg|Image uploaded from iOS> and commented: See? Eating healthy this weekend. :relaxed::+1:",
        "file": {
            "id": "F45S19ZG9",
            "created": 1487268542,
            "timestamp": 1487268542,
            "name": "Image uploaded from iOS.jpg",
            "title": "Image uploaded from iOS",
            "mimetype": "image\/jpeg",
            "filetype": "jpg",
            "pretty_type": "JPEG",
            "user": "U3SJ6J3CZ",
            "editable": false,
            "size": 3047539,
            "mode": "hosted",
            "is_external": false,
            "external_type": "",
            "is_public": true,
            "public_url_shared": false,
            "display_as_bot": false,
            "username": "",
            "url_private": "https:\/\/files.slack.com\/files-pri\/T3P35HN56-F45S19ZG9\/image_uploaded_from_ios.jpg?t=xoxe-125107600176-274565733731-275515188566-de7bec41ca",
            "url_private_download": "https:\/\/files.slack.com\/files-pri\/T3P35HN56-F45S19ZG9\/download\/image_uploaded_from_ios.jpg?t=xoxe-125107600176-274565733731-275515188566-de7bec41ca",
            "thumb_64": "https:\/\/files.slack.com\/files-tmb\/T3P35HN56-F45S19ZG9-5df5423e18\/image_uploaded_from_ios_64.jpg?t=xoxe-125107600176-274565733731-275515188566-de7bec41ca",
            "thumb_80": "https:\/\/files.slack.com\/files-tmb\/T3P35HN56-F45S19ZG9-5df5423e18\/image_uploaded_from_ios_80.jpg?t=xoxe-125107600176-274565733731-275515188566-de7bec41ca",
            "thumb_360": "https:\/\/files.slack.com\/files-tmb\/T3P35HN56-F45S19ZG9-5df5423e18\/image_uploaded_from_ios_360.jpg?t=xoxe-125107600176-274565733731-275515188566-de7bec41ca",
            "thumb_360_w": 270,
            "thumb_360_h": 360,
            "thumb_480": "https:\/\/files.slack.com\/files-tmb\/T3P35HN56-F45S19ZG9-5df5423e18\/image_uploaded_from_ios_480.jpg?t=xoxe-125107600176-274565733731-275515188566-de7bec41ca",
            "thumb_480_w": 360,
            "thumb_480_h": 480,
            "thumb_160": "https:\/\/files.slack.com\/files-tmb\/T3P35HN56-F45S19ZG9-5df5423e18\/image_uploaded_from_ios_160.jpg?t=xoxe-125107600176-274565733731-275515188566-de7bec41ca",
            "thumb_720": "https:\/\/files.slack.com\/files-tmb\/T3P35HN56-F45S19ZG9-5df5423e18\/image_uploaded_from_ios_720.jpg?t=xoxe-125107600176-274565733731-275515188566-de7bec41ca",
            "thumb_720_w": 540,
            "thumb_720_h": 720,
            "thumb_960": "https:\/\/files.slack.com\/files-tmb\/T3P35HN56-F45S19ZG9-5df5423e18\/image_uploaded_from_ios_960.jpg?t=xoxe-125107600176-274565733731-275515188566-de7bec41ca",
            "thumb_960_w": 720,
            "thumb_960_h": 960,
            "thumb_1024": "https:\/\/files.slack.com\/files-tmb\/T3P35HN56-F45S19ZG9-5df5423e18\/image_uploaded_from_ios_1024.jpg?t=xoxe-125107600176-274565733731-275515188566-de7bec41ca",
            "thumb_1024_w": 768,
            "thumb_1024_h": 1024,
            "image_exif_rotation": 1,
            "original_w": 4032,
            "original_h": 3024,
            "permalink": "https:\/\/nerdpartytrivia.slack.com\/files\/U3SJ6J3CZ\/F45S19ZG9\/image_uploaded_from_ios.jpg",
            "permalink_public": "https:\/\/slack-files.com\/T3P35HN56-F45S19ZG9-73451062bd",
            "channels": [],
            "groups": [],
            "ims": [],
            "comments_count": 1,
            "initial_comment": {
                "id": "Fc46K75B0V",
                "created": 1487268542,
                "timestamp": 1487268542,
                "user": "U3SJ6J3CZ",
                "is_intro": true,
                "comment": "See? Eating healthy this weekend. :relaxed::+1:"
            }
        },
        "user": "U3SJ6J3CZ",
        "upload": true,
        "display_as_bot": false,
        "username": "kurt",
        "bot_id": null,
        "upload_reply_to": "449362E8-9F22-49BC-8016-7B3E2B62880B",
        "ts": "1487268552.000138"
    },
    {
        "type": "message",
        "user": "U3SJ6J3CZ",
        "text": "Narnia is even looking on in disbelief!",
        "ts": "1487268584.000139"
    },
    {
        "type": "message",
        "user": "U3TAVES85",
        "text": "Does anyone who's going to be at hq have a mini displayport to dvi cable I could use?",
        "ts": "1487269003.000140"
    },
    {
        "type": "message",
        "user": "U3TAVES85",
        "text": "Or mdp to hdmi would work too",
        "ts": "1487269401.000141"
    },
    {
        "type": "message",
        "user": "U3PTX9WER",
        "text": "I might. When I get home I'll post pics of what I have.",
        "ts": "1487270704.000142"
    },
    {
        "type": "message",
        "user": "U3SJ6J3CZ",
        "text": "I'm expecting a few questions about the movie \"Twister\". ",
        "ts": "1487270921.000143",
        "reactions": [
            {
                "name": "+1",
                "users": [
                    "U3QAZR6D6"
                ],
                "count": 1
            }
        ]
    },
    {
        "type": "message",
        "user": "U3TAVES85",
        "text": "Also maybe The Perfect Storm",
        "ts": "1487270964.000144"
    },
    {
        "type": "message",
        "user": "U3U0Z9F4K",
        "text": "Don't forget Days of Thunder!!!",
        "ts": "1487271115.000145"
    },
    {
        "type": "message",
        "user": "U3SJ6J3CZ",
        "text": "And Stephen King's \"Storm of the Century\"! ",
        "ts": "1487271379.000146"
    },
    {
        "type": "message",
        "user": "U3SJ6J3CZ",
        "text": "Im also expecting a question about Castle Thunder. <https:\/\/en.m.wikipedia.org\/wiki\/Castle_thunder_(sound_effect)>",
        "attachments": [
            {
                "title": "Castle thunder (sound effect)",
                "title_link": "https:\/\/en.m.wikipedia.org\/wiki\/Castle_thunder_(sound_effect)",
                "author_name": "Wikipedia",
                "author_link": "http:\/\/en.wikipedia.org\/",
                "text": "Castle thunder is a sound effect that consists of the sound of a loud thunderclap during a rainstorm. It was originally recorded for the 1931 film Frankenstein, and has since been used in dozens of films, television programs, and commercials.",
                "fallback": "wikipedia: Castle thunder (sound effect)",
                "service_icon": "https:\/\/a.slack-edge.com\/bfaba\/img\/unfurl_icons\/wikipedia.png",
                "id": 1
            }
        ],
        "ts": "1487272006.000147",
        "reactions": [
            {
                "name": "+1",
                "users": [
                    "U3QAZR6D6"
                ],
                "count": 1
            }
        ]
    },
    {
        "type": "message",
        "user": "U3U0Z9F4K",
        "text": "I'll just leave this here.  You never know what they could ask about! <https:\/\/www.thunderfromdownunder.com\/>",
        "attachments": [
            {
                "title": "Thunder From Down Under",
                "title_link": "https:\/\/www.thunderfromdownunder.com\/",
                "text": "The PERFECT Girls' Night Outback! Australia's HOTTEST Export hits the Vegas stage every night to deliver a fully interactive and intimate experience.",
                "fallback": "Thunder From Down Under",
                "from_url": "https:\/\/www.thunderfromdownunder.com\/",
                "service_name": "thunderfromdownunder.com",
                "id": 1
            }
        ],
        "ts": "1487272156.000149",
        "reactions": [
            {
                "name": "chipmunk",
                "users": [
                    "U3P3ZG1Q9",
                    "U3QAZR6D6"
                ],
                "count": 2
            }
        ]
    },
    {
        "type": "message",
        "user": "U3SJ6J3CZ",
        "text": "Also: <http:\/\/www.homes.com\/real-estate\/disaster-prep\/sharknado\/>",
        "edited": {
            "user": "U3SJ6J3CZ",
            "ts": "1487278384.000000"
        },
        "ts": "1487276265.000154"
    },
    {
        "type": "message",
        "user": "U3PSHA2RY",
        "text": "Oh god. How did weather turn out to be such a terrifying theme? :weary: 🦈",
        "ts": "1487277266.000156"
    },
    {
        "type": "message",
        "subtype": "file_share",
        "text": "<@U3SJ6J3CZ> uploaded a file: <https:\/\/nerdpartytrivia.slack.com\/files\/U3SJ6J3CZ\/F46K76D26\/image_uploaded_from_ios.jpg|Image uploaded from iOS> and commented: I want to read this!",
        "file": {
            "id": "F46K76D26",
            "created": 1487277350,
            "timestamp": 1487277350,
            "name": "Image uploaded from iOS.jpg",
            "title": "Image uploaded from iOS",
            "mimetype": "image\/jpeg",
            "filetype": "jpg",
            "pretty_type": "JPEG",
            "user": "U3SJ6J3CZ",
            "editable": false,
            "size": 382067,
            "mode": "hosted",
            "is_external": false,
            "external_type": "",
            "is_public": true,
            "public_url_shared": false,
            "display_as_bot": false,
            "username": "",
            "url_private": "https:\/\/files.slack.com\/files-pri\/T3P35HN56-F46K76D26\/image_uploaded_from_ios.jpg?t=xoxe-125107600176-274565733731-275515188566-de7bec41ca",
            "url_private_download": "https:\/\/files.slack.com\/files-pri\/T3P35HN56-F46K76D26\/download\/image_uploaded_from_ios.jpg?t=xoxe-125107600176-274565733731-275515188566-de7bec41ca",
            "thumb_64": "https:\/\/files.slack.com\/files-tmb\/T3P35HN56-F46K76D26-bb0f152f05\/image_uploaded_from_ios_64.jpg?t=xoxe-125107600176-274565733731-275515188566-de7bec41ca",
            "thumb_80": "https:\/\/files.slack.com\/files-tmb\/T3P35HN56-F46K76D26-bb0f152f05\/image_uploaded_from_ios_80.jpg?t=xoxe-125107600176-274565733731-275515188566-de7bec41ca",
            "thumb_360": "https:\/\/files.slack.com\/files-tmb\/T3P35HN56-F46K76D26-bb0f152f05\/image_uploaded_from_ios_360.jpg?t=xoxe-125107600176-274565733731-275515188566-de7bec41ca",
            "thumb_360_w": 202,
            "thumb_360_h": 360,
            "thumb_480": "https:\/\/files.slack.com\/files-tmb\/T3P35HN56-F46K76D26-bb0f152f05\/image_uploaded_from_ios_480.jpg?t=xoxe-125107600176-274565733731-275515188566-de7bec41ca",
            "thumb_480_w": 270,
            "thumb_480_h": 480,
            "thumb_160": "https:\/\/files.slack.com\/files-tmb\/T3P35HN56-F46K76D26-bb0f152f05\/image_uploaded_from_ios_160.jpg?t=xoxe-125107600176-274565733731-275515188566-de7bec41ca",
            "thumb_720": "https:\/\/files.slack.com\/files-tmb\/T3P35HN56-F46K76D26-bb0f152f05\/image_uploaded_from_ios_720.jpg?t=xoxe-125107600176-274565733731-275515188566-de7bec41ca",
            "thumb_720_w": 405,
            "thumb_720_h": 720,
            "thumb_960": "https:\/\/files.slack.com\/files-tmb\/T3P35HN56-F46K76D26-bb0f152f05\/image_uploaded_from_ios_960.jpg?t=xoxe-125107600176-274565733731-275515188566-de7bec41ca",
            "thumb_960_w": 540,
            "thumb_960_h": 960,
            "thumb_1024": "https:\/\/files.slack.com\/files-tmb\/T3P35HN56-F46K76D26-bb0f152f05\/image_uploaded_from_ios_1024.jpg?t=xoxe-125107600176-274565733731-275515188566-de7bec41ca",
            "thumb_1024_w": 576,
            "thumb_1024_h": 1024,
            "image_exif_rotation": 1,
            "original_w": 750,
            "original_h": 1334,
            "permalink": "https:\/\/nerdpartytrivia.slack.com\/files\/U3SJ6J3CZ\/F46K76D26\/image_uploaded_from_ios.jpg",
            "permalink_public": "https:\/\/slack-files.com\/T3P35HN56-F46K76D26-e1e6781ac0",
            "channels": [],
            "groups": [],
            "ims": [],
            "comments_count": 1,
            "initial_comment": {
                "id": "Fc46MU5GAH",
                "created": 1487277350,
                "timestamp": 1487277350,
                "user": "U3SJ6J3CZ",
                "is_intro": true,
                "comment": "I want to read this!"
            },
            "reactions": [
                {
                    "name": "+1",
                    "users": [
                        "U3PTX9WER"
                    ],
                    "count": 1
                }
            ]
        },
        "user": "U3SJ6J3CZ",
        "upload": true,
        "display_as_bot": false,
        "username": "kurt",
        "bot_id": null,
        "upload_reply_to": "B619A60F-8C24-4ACB-B126-098ADF916D1E",
        "ts": "1487277350.000157"
    }
]